{"TdwAFndruph8+alKf8+FCw==":"mbr-121x181.jpg","MO93ZBRFvWJ/FLLYn28t3Q==":"png-clipart-stretching-exercise-fitness-centre-computer-icons-personal-trainer-others-miscellaneous-angle-81x88.png","R4MQHiFvVoDNl2y/BQ2PYA==":"png-clipart-fitness-centre-physical-fitness-computer-icons-weight-training-physical-exercise-psd-gym-miscellaneous-text-111x63.png","HeiysN+Ptg/6LTlZnT3grw==":"pngegg-214x214.png","m9v/QtCrjlYBVcDZjFdIMg==":"mbr-121x72.jpg","2Ln0edb2gc4nX4dr1/YZ1g==":"logo-204x204.jpg","XvSiASCTn3AXSHvzfy3mUA==":"logo-121x121.png","IeRHni6sepMSoSGuoxcw7Q==":"logo-1-121x121.png","3LgiGy042s69l7dWYz5pjA==":"spanish-with-ari-01-128x94_1.png","NFhkMwycYcQzKEyhkSOJXg==":"spanish%20with%20ari%2002-187x107.jpg","3nTLmH0LRrbExlsPyR18hg==":"spanish%20with%20ari%2001-240x176.png","G1twj5rhbJ2Xms4tNVKSZA==":"whatsapp%20image%202020-10-06%20at%209.54.01%20pm-187x187.jpg","/lYSVX6Rk1d1tulwsHURnw==":"photo-1597481126763-137x137.jpg","+WnWmonSu0EHs23iW5167Q==":"14-2000x1156.jpg","qXjHTg8RqLbYl7Scg59QNQ==":"32-2000x2987.jpg","jqh7+7ihJ1RF9S5RCxOZ3w==":"25-2000x1082.jpg","K7NifpcLg2QpbLXZvMXD0g==":"22-2000x1206.jpg","93qrAn7rilrwZ6EzIhF2Hg==":"43-2000x1334.jpg"}